pyrfm/__init__.py
pyrfm/core.py
pyrfm/geometry.py
pyrfm/optimize.py
pyrfm/rk.py
pyrfm/utils.py
pyrfm/visualizer.py
pyrfm/voronoi.py
pyrfm-0.3.6.dist-info/licenses/LICENSE
pyrfm-0.3.6.dist-info/METADATA
pyrfm-0.3.6.dist-info/WHEEL
pyrfm-0.3.6.dist-info/top_level.txt
pyrfm-0.3.6.dist-info/RECORD
