Metadata-Version: 2.4
Name: pyrfm
Version: 0.3.6
Summary: Random Feature Method (RFM) tools in Python
Home-page: https://ifaay.github.io
Author: Yifei Sun
Author-email: yfsun99@stu.suda.edu.cn
Classifier: Programming Language :: Python :: 3
Classifier: License :: OSI Approved :: MIT License
Classifier: Operating System :: OS Independent
Requires-Python: >=3.10
License-File: LICENSE
Requires-Dist: torch>=2.1.0
Requires-Dist: numpy>=1.23
Requires-Dist: pandas>=1.5
Requires-Dist: matplotlib>=3.5
Requires-Dist: scipy>=1.9
Dynamic: author
Dynamic: author-email
Dynamic: classifier
Dynamic: description
Dynamic: description-content-type
Dynamic: home-page
Dynamic: license-file
Dynamic: requires-dist
Dynamic: requires-python
Dynamic: summary
